rest_models/__init__.py
rest_models/checks.py
rest_models/router.py
rest_models/storage.py
rest_models/test.py
rest_models/utils.py
rest_models/backend/__init__.py
rest_models/backend/auth.py
rest_models/backend/base.py
rest_models/backend/client.py
rest_models/backend/compiler.py
rest_models/backend/connexion.py
rest_models/backend/creation.py
rest_models/backend/exceptions.py
rest_models/backend/features.py
rest_models/backend/introspection.py
rest_models/backend/middlewares.py
rest_models/backend/operations.py
rest_models/backend/schema.py
rest_models/backend/utils.py
rest_models/backend/exec/resty
django_rest_models-3.0.2.dist-info/LICENSE.md
django_rest_models-3.0.2.dist-info/METADATA
django_rest_models-3.0.2.dist-info/WHEEL
django_rest_models-3.0.2.dist-info/top_level.txt
django_rest_models-3.0.2.dist-info/RECORD
