Metadata-Version: 2.2
Name: django-rest-models
Version: 3.0.2
Summary: A Django fake ORM model that query an RestAPI instead of a database.
Author-email: Darius BERNARD <darius@yupeek.com>
License: # License
Project-URL: source, https://github.com/Yupeek/django-rest-models
Keywords: django,rest,models,API,ORM
Classifier: Development Status :: 4 - Beta
Classifier: Intended Audience :: Developers
Classifier: License :: OSI Approved :: BSD License
Classifier: Programming Language :: Python :: 3
Classifier: Programming Language :: Python :: 3.9
Classifier: Programming Language :: Python :: 3.10
Classifier: Programming Language :: Python :: 3.11
Classifier: Programming Language :: Python :: 3.12
Classifier: Operating System :: OS Independent
Classifier: Topic :: Software Development :: Libraries
Classifier: Topic :: Utilities
Classifier: Environment :: Web Environment
Classifier: Framework :: Django
Requires-Python: >=3.9
License-File: LICENSE.md
Requires-Dist: django<5.2,>=4.2
Requires-Dist: requests
Requires-Dist: unidecode
